RFExplorer/RFE6GEN_CalibrationData.py
RFExplorer/RFEAmplitudeTableData.py
RFExplorer/RFEConfiguration.py
RFExplorer/RFESweepData.py
RFExplorer/RFESweepDataCollection.py
RFExplorer/RFE_Common.py
RFExplorer/RFExplorer.py
RFExplorer/ReceiveSerialThread.py
RFExplorer/__init__.py
RFExplorer-1.33.2106.3.dist-info/LICENSE.txt
RFExplorer-1.33.2106.3.dist-info/METADATA
RFExplorer-1.33.2106.3.dist-info/WHEEL
RFExplorer-1.33.2106.3.dist-info/top_level.txt
RFExplorer-1.33.2106.3.dist-info/RECORD
