Metadata-Version: 2.1
Name: RFExplorer
Version: 1.33.2106.3
Summary: RF Explorer libraries and examples for Python 3.5
Home-page: https://github.com/RFExplorer/RFExplorer-for-Python/wiki
Author: RF Explorer
Author-email: contact@rf-explorer.com
License: GNU LGPLv3
Download-URL: https://github.com/RFExplorer/RFExplorer-for-Python/wiki
Keywords: rfexplorer iot development analyzer spectrum
Platform: UNKNOWN
Classifier: Development Status :: 5 - Production/Stable
Classifier: Intended Audience :: Developers
Classifier: Intended Audience :: System Administrators
Classifier: Intended Audience :: Education
Classifier: Topic :: Utilities
Classifier: Topic :: Scientific/Engineering
Classifier: License :: OSI Approved :: GNU Lesser General Public License v3 (LGPLv3)
Classifier: Programming Language :: Python :: 3.5
Requires-Dist: PySerial
